basicModules/Roblox.py
basicModules/Shell.py
basicModules/Web.py
basicModules/__init__.py
basicModules-1.0.4.dist-info/METADATA
basicModules-1.0.4.dist-info/WHEEL
basicModules-1.0.4.dist-info/top_level.txt
basicModules-1.0.4.dist-info/RECORD
