Metadata-Version: 2.1
Name: basicModules
Version: 1.0.4
Summary: A python package gives basic modules.
Home-page: https://github.com/Zach-Tolentino-161/robloxFunctions
Author: PandaGamerYT
Author-email: zachgameryt08@gmail.com
License: MIT
Platform: UNKNOWN
Requires-Python: >=3.8
Requires-Dist: requests
Requires-Dist: robloxFunctions
